model/__init__.py
model/swin_transformer.py
swin_transformer/__init__.py
swin_transformer/swin_transformer.py
swin_transformer_pytorch/__init__.py
swin_transformer_pytorch/swin_transformer.py
swin_transformer_pytorch-0.4.1.dist-info/LICENSE
swin_transformer_pytorch-0.4.1.dist-info/METADATA
swin_transformer_pytorch-0.4.1.dist-info/WHEEL
swin_transformer_pytorch-0.4.1.dist-info/top_level.txt
swin_transformer_pytorch-0.4.1.dist-info/RECORD
