Metadata-Version: 2.1
Name: swin-transformer-pytorch
Version: 0.4.1
Summary: Swin Transformer - Pytorch
Home-page: https://github.com/berniwal/swin-transformer-pytorch
Author: Bernhard Walser
Author-email: berniwal1997@hotmail.com
License: MIT
Keywords: artificial intelligence,attention mechanism,image recognition
Platform: UNKNOWN
Classifier: Development Status :: 4 - Beta
Classifier: Intended Audience :: Developers
Classifier: Topic :: Scientific/Engineering :: Artificial Intelligence
Classifier: License :: OSI Approved :: MIT License
Classifier: Programming Language :: Python :: 3.6 
Requires-Dist: torch (>=1.8.1)
Requires-Dist: einops (>=0.3.0)
